setup.py
lxc/__init__.py
pylxclite.egg-info/PKG-INFO
pylxclite.egg-info/SOURCES.txt
pylxclite.egg-info/dependency_links.txt
pylxclite.egg-info/top_level.txt
pylxclite.egg-info/zip-safe