Metadata-Version: 1.0
Name: pylxclite
Version: 0.0.3
Summary: A python wrapper for Linux Containers (LXC)
Home-page: https://github.com/Unixlike/pylxclite
Author: Camel
Author-email: 393789775@qq.com
License: LGPLv3
Platform: UNKNOWN
Classifier: Development Status :: 5 - Production/Stable
Classifier: Intended Audience :: System Administrators
Classifier: License :: OSI Approved :: GNU Library or Lesser General Public License (LGPL)
Classifier: Operating System :: POSIX :: Linux
Classifier: Programming Language :: Python :: 2.6
Classifier: Topic :: System :: Systems Administration
